{
  "project_info": {
    "project_number": "803759764285",
    "project_id": "dream-bc223",
    "storage_bucket": "dream-bc223.appspot.com"
  },
  "client": [
    {
      "client_info": {
        "mobilesdk_app_id": "1:803759764285:android:ea88f58b13f5688dff0b54",
        "android_client_info": {
          "package_name": "com.dream.dreamproject"
        }
      },
      "oauth_client": [
        {
          "client_id": "803759764285-maiq5snc867bm22f0a4aiapjac8a46bk.apps.googleusercontent.com",
          "client_type": 1,
          "android_info": {
            "package_name": "com.dream.dreamproject",
            "certificate_hash": "f86a0ebf06cd57ff23c6509ca85f8af4ebe47701"
          }
        },
        {
          "client_id": "803759764285-fphq61a2bo5vqg7n72el0l21fkflufr8.apps.googleusercontent.com",
          "client_type": 3
        }
      ],
      "api_key": [
        {
          "current_key": "AIzaSyAeLCeceQ0HMi2EPoJS6FFFWeROaio-Y9I"
        }
      ],
      "services": {
        "appinvite_service": {
          "other_platform_oauth_client": [
            {
              "client_id": "803759764285-fphq61a2bo5vqg7n72el0l21fkflufr8.apps.googleusercontent.com",
              "client_type": 3
            }
          ]
        }
      }
    }
  ],
  "configuration_version": "1"
}